{
  "nome_fantasia": "Rogerio Mes",
  "name": "Rogerinos",
  "document": "43485794000133",
  "cellphone": "47999950731",
  "email": "rogeriojungjunior1@gmail.com",
  "ticket_medio": 50002,
  "numero": "4001",
  "complemento": "casa1",
  "rua": "erich jung2 ",
  "bairro": "benedito3",
  "cidade": "INDAIAL1",
  "estado": "RS",
  "pais": "Brasil",
  "cpf": "05642500902",
  "nome_mae": "Maria Regina",
  "birthDate": "1985-02-01T00:00:00",
  "postbackUrl": "https://testani.com/teste-api",
  "status": "0",
  "motivo_status": "batata1",
  "account": {
    "id": "7921e3eb-c680-11ec-a571-002248256060",
    "agency": "0001",
    "number": "44452675",
    "bankCode": "260",
    "pixKey": null
  }
}